stubborn/__init__.py
stubborn/__main__.py
stubborn/bootstrap.py
stubborn/callbackino.py
stubborn/command_group.py
stubborn/defaults.py
stubborn/exceptions.py
stubborn/hand_coded_policies.py
stubborn/plotting.py
stubborn/running.py
stubborn/stubborn_config.py
stubborn/stubborn_env.py
stubborn/stubborn_state.py
stubborn/utils.py
stubborn/county/__init__.py
stubborn/county/base_env.py
stubborn/county/base_state.py
stubborn/county/constants.py
stubborn/county/csv_tools.py
stubborn/county/filtros.py
stubborn/county/misc.py
stubborn/county/policing.py
stubborn/county/thready_krueger.py
stubborn/county/typing.py
stubborn-0.0.2.dist-info/LICENSE
stubborn-0.0.2.dist-info/METADATA
stubborn-0.0.2.dist-info/WHEEL
stubborn-0.0.2.dist-info/top_level.txt
stubborn-0.0.2.dist-info/RECORD
