Metadata-Version: 2.1
Name: stubborn
Version: 0.0.2
Summary: An Environment for Evaluating Stubbornness between Agents with Aligned Incentives
Home-page: https://github.com/cool-RR/stubborn
Author: Ram Rachum
Author-email: ram@rachum.com
Classifier: Development Status :: 3 - Alpha
Classifier: Intended Audience :: Science/Research
Classifier: Topic :: Scientific/Engineering :: Artificial Intelligence
Classifier: Programming Language :: Python :: 3.10
Classifier: Programming Language :: Python :: Implementation :: CPython
Classifier: License :: OSI Approved :: MIT License
License-File: LICENSE
Requires-Dist: click (==8.0.4)
Requires-Dist: frozendict (==2.3.7)
Requires-Dist: more-itertools (==9.1.0)
Requires-Dist: numpy (==1.23.5)
Requires-Dist: pandas (==2.0.0)
Requires-Dist: plotly (==5.14.1)
Requires-Dist: pyyaml (==6.0)
Requires-Dist: ray[rllib] (==2.1.0)
Requires-Dist: tensorflow (==2.12.0)
Provides-Extra: tests
Requires-Dist: pytest ; extra == 'tests'
